[{"index": 1442, "x": 0, "y": 27, "width": 18, "height": 30}, {"index": 1443, "x": 52, "y": 0, "width": 17, "height": 14}, {"index": 1444, "x": 20, "y": 58, "width": 17, "height": 11}, {"index": 1445, "x": 27, "y": 0, "width": 17, "height": 13}, {"index": 1446, "x": 27, "y": 13, "width": 17, "height": 17}, {"index": 1447, "x": 11, "y": 0, "width": 16, "height": 27}, {"index": 1448, "x": 44, "y": 14, "width": 18, "height": 32}, {"index": 1449, "x": 18, "y": 45, "width": 19, "height": 13}, {"index": 1450, "x": 33, "y": 30, "width": 11, "height": 13}, {"index": 1451, "x": 62, "y": 14, "width": 10, "height": 12}, {"index": 1452, "x": 37, "y": 46, "width": 17, "height": 23}, {"index": 1453, "x": 40, "y": 69, "width": 11, "height": 12}, {"index": 1454, "x": 44, "y": 0, "width": 8, "height": 13}, {"index": 1455, "x": 62, "y": 26, "width": 11, "height": 13}, {"index": 1456, "x": 54, "y": 46, "width": 19, "height": 29}, {"index": 1457, "x": 12, "y": 58, "width": 8, "height": 23}, {"index": 1458, "x": 0, "y": 57, "width": 12, "height": 21}, {"index": 1459, "x": 18, "y": 30, "width": 15, "height": 15}, {"index": 1460, "x": 20, "y": 69, "width": 20, "height": 9}]